MANIFEST.in
README.rst
VERSION
requirements.txt
setup.py
src/flask_tat/__init__.py
src/flask_tat/base.py
src/flask_tat/engine.py
src/flask_tat/http2kafka.py
src/flask_tat.egg-info/PKG-INFO
src/flask_tat.egg-info/SOURCES.txt
src/flask_tat.egg-info/dependency_links.txt
src/flask_tat.egg-info/requires.txt
src/flask_tat.egg-info/top_level.txt
src/flask_tat.egg-info/zip-safe