Metadata-Version: 1.1
Name: flask-tat
Version: 0.0.7
Summary: Flask TAT client
Home-page: https://github.com/cdumay/flask-tat
Author: Cedric DUMAY
Author-email: cedric.dumay@gmail.com
License: Apache License
Platform: UNKNOWN
Classifier: Programming Language :: Python
